nvidia/__init__.py
nvidia/cuda_sanitizer_api/__init__.py
nvidia/cuda_sanitizer_api/bin/InterceptorInjectionTarget.dll
nvidia/cuda_sanitizer_api/bin/TreeLauncherTargetInjection.dll
nvidia/cuda_sanitizer_api/bin/__init__.py
nvidia/cuda_sanitizer_api/bin/sanitizer-collection.dll
nvidia/cuda_sanitizer_api/bin/sanitizer-public.dll
nvidia/cuda_sanitizer_api/include/__init__.py
nvidia/cuda_sanitizer_api/include/generated_cudaD3D10_meta.h
nvidia/cuda_sanitizer_api/include/generated_cudaD3D11_meta.h
nvidia/cuda_sanitizer_api/include/generated_cudaD3D9_meta.h
nvidia/cuda_sanitizer_api/include/generated_cudaGL_meta.h
nvidia/cuda_sanitizer_api/include/generated_cuda_d3d10_interop_meta.h
nvidia/cuda_sanitizer_api/include/generated_cuda_d3d11_interop_meta.h
nvidia/cuda_sanitizer_api/include/generated_cuda_d3d9_interop_meta.h
nvidia/cuda_sanitizer_api/include/generated_cuda_gl_interop_meta.h
nvidia/cuda_sanitizer_api/include/generated_cuda_meta.h
nvidia/cuda_sanitizer_api/include/generated_cuda_profiler_api_meta.h
nvidia/cuda_sanitizer_api/include/generated_cuda_runtime_api_meta.h
nvidia/cuda_sanitizer_api/include/sanitizer.h
nvidia/cuda_sanitizer_api/include/sanitizer_barrier.h
nvidia/cuda_sanitizer_api/include/sanitizer_callbacks.h
nvidia/cuda_sanitizer_api/include/sanitizer_driver_cbid.h
nvidia/cuda_sanitizer_api/include/sanitizer_memory.h
nvidia/cuda_sanitizer_api/include/sanitizer_patching.h
nvidia/cuda_sanitizer_api/include/sanitizer_result.h
nvidia/cuda_sanitizer_api/include/sanitizer_runtime_cbid.h
nvidia/cuda_sanitizer_api/include/sanitizer_stream.h
nvidia_cuda_sanitizer_api_cu11-11.8.86.dist-info/License.txt
nvidia_cuda_sanitizer_api_cu11-11.8.86.dist-info/METADATA
nvidia_cuda_sanitizer_api_cu11-11.8.86.dist-info/WHEEL
nvidia_cuda_sanitizer_api_cu11-11.8.86.dist-info/top_level.txt
nvidia_cuda_sanitizer_api_cu11-11.8.86.dist-info/RECORD
